{"data":{"postgres":{"establishment":[{"establishmentid":"3874","name":"Covenant East /Lifeskills","address":"7600 Goethe St","owner":"Detroit Board of Education","licenseNumber":"064097","licenseType":"Fixed Establishment","establishmentType":"Charter School","establishmentStatus":"Open","riskCategory":"Medium","reviewFrequencyDays":"210.0","inspectionsByEstablishmentidList":[{"inspectionid":"44553","inspectionDate":"2018-12-20T00:00:00","inspectionType":"Routine Inspection","inCompliance":"Yes","violationsByInspectionidList":[]},{"inspectionid":"42531","inspectionDate":"2018-06-14T00:00:00","inspectionType":"Routine Inspection","inCompliance":"Yes","violationsByInspectionidList":[]},{"inspectionid":"40790","inspectionDate":"2017-11-16T00:00:00","inspectionType":"Routine Inspection","inCompliance":"Yes","violationsByInspectionidList":[]},{"inspectionid":"39014","inspectionDate":"2017-06-14T00:00:00","inspectionType":"Routine Inspection","inCompliance":"Yes","violationsByInspectionidList":[]},{"inspectionid":"37440","inspectionDate":"2016-12-21T00:00:00","inspectionType":"Routine Inspection","inCompliance":"Yes","violationsByInspectionidList":[]}]}]}},"pageContext":{"eid":"3874"}}