{"data":{"site":{"pathPrefix":"/restaurant-inspections"},"postgres":{"establishment":[{"establishmentid":"732","name":"Sidekicks Saloon","address":"7023 Chatsfield St","zipcode":"48209","owner":"Sharon Cicotte","licenseNumber":"034708","licenseType":"Fixed Establishment","establishmentType":"Food Service Establishment","establishmentStatus":"Open","riskCategory":null,"reviewFrequencyDays":"365.0","coords":"-83.11525,42.30899","geojson":{"id":"732","type":"Feature","geometry":{"type":"Point","coordinates":[-83.1152539459999,42.3089897580001]},"properties":{"name":"Sidekicks Saloon","owner":"Sharon Cicotte","address":"7023 Chatsfield St","zipcode":"48209","license_type":"Fixed Establishment","risk_category":null,"license_number":"034708","establishmentid":"732","establishment_type":"Food Service Establishment","establishment_status":"Open","review_frequency_days":"365.0","most_recent_license_date":"5/29/2019"}},"nearbyList":[{"establishmentid":"703","name":"Roberto Clemente Elementary","address":"1551 Beard St","zipcode":"48209"},{"establishmentid":"3304","name":"Cesar Chavez Middle School","address":"6782 Goldsmith St","zipcode":"48209"},{"establishmentid":"735","name":"Happy Bar","address":"1247 Green St N","zipcode":"48209"},{"establishmentid":"1650","name":"Dino's Cafe Inc.","address":"1601 Waterman St","zipcode":"48209"},{"establishmentid":"2343","name":"Cesar Chavez Academy High School","address":"1761 Waterman St","zipcode":"48209"},{"establishmentid":"3926","name":"Taqueria Camino Real","address":"1100 Central","zipcode":"48209"},{"establishmentid":"51622712","name":"Tacos Regios Mexican Grill","address":"2257 Waterman St","zipcode":"48209"},{"establishmentid":"51623131","name":"Ice Cream & Cafe La Niña","address":"2257 Waterman","zipcode":"48209"},{"establishmentid":"675","name":"Motz  Restaurant Inc","address":"7208 Fort St W","zipcode":"48209"},{"establishmentid":"4792","name":"Las Palmas Neveria Y Cafeteria","address":"7009 Vernor Hwy","zipcode":"48209"}],"inspectionsByEstablishmentidList":[{"inspectionid":"45812","inspectionDate":"2019-04-04T00:00:00","inspectionType":"Routine Inspection","inCompliance":"Yes","violationsByInspectionidList":[]},{"inspectionid":"38128","inspectionDate":"2017-03-03T00:00:00","inspectionType":"Routine Inspection","inCompliance":"Yes","violationsByInspectionidList":[]}]}],"maxInspectionDate":[{"inspectionDate":"2019-10-31T00:00:00"}]}},"pageContext":{"eid":"732"}}