{"data":{"postgres":{"establishment":[{"establishmentid":"2824","name":"Ross-Hill Academy","address":"3111 Elmwood","zipcode":"48207","owner":"N.Williams-principal","licenseNumber":"050727","licenseType":"Fixed Establishment","mostRecentLicenseDate":"5/1/2017","establishmentType":"Non-Public School","establishmentStatus":"Temporarily Closed","riskCategory":null,"reviewFrequencyDays":"210.0","geom":"0101000020E6100000146EB474A9C154C0F0775D69A02D4540","inspectionsByEstablishmentidList":[{"inspectionid":"39069","establishmentid":"2824","name":"Ross-Hill Academy","inspectionDate":"2017-06-20T00:00:00","inspectionType":"Routine Inspection","inspectorid":"87","pcount":"0","pfcount":"0","ccount":"0","criticalcount":"0","noncritical":"0","correctedcritical":"0","inCompliance":"Yes","violationsByInspectionidList":[]},{"inspectionid":"37431","establishmentid":"2824","name":"Ross-Hill Academy","inspectionDate":"2016-12-20T00:00:00","inspectionType":"Routine Inspection","inspectorid":"87","pcount":"0","pfcount":"0","ccount":"0","criticalcount":"0","noncritical":"0","correctedcritical":"0","inCompliance":"Yes","violationsByInspectionidList":[]}]}]}},"pageContext":{"eid":"2824"}}