{"errors":[],"warnings":[],"namedChunkGroups":{"app":{"chunks":[9,3],"assets":["webpack-runtime-a1cdc5a2a5df1cf7ad58.js","webpack-runtime-a1cdc5a2a5df1cf7ad58.js.map","app-832c7fb7645773a12e84.js","app-832c7fb7645773a12e84.js.map"],"children":{},"childAssets":{}},"component---src-templates-establishment-page-js":{"chunks":[0,1,2,10,7],"assets":["styles.d19f409ceaaf3db55427.css","styles-efe02eb7393a36b75825.js","styles-efe02eb7393a36b75825.js.map","1-834dfe3fd661fe7c9a88.js","1-834dfe3fd661fe7c9a88.js.map","2-e6c9c74e3cf811e0f2ab.js","2-e6c9c74e3cf811e0f2ab.js.map","10-1bfaa1cd3a83ccf05927.js","10-1bfaa1cd3a83ccf05927.js.map","component---src-templates-establishment-page-js-658ebfa8996f0b5efdd1.js","component---src-templates-establishment-page-js-658ebfa8996f0b5efdd1.js.map"],"children":{},"childAssets":{}},"component---src-pages-404-js":{"chunks":[0,1,4],"assets":["styles.d19f409ceaaf3db55427.css","styles-efe02eb7393a36b75825.js","styles-efe02eb7393a36b75825.js.map","1-834dfe3fd661fe7c9a88.js","1-834dfe3fd661fe7c9a88.js.map","component---src-pages-404-js-a99c0d5feb017d0a2bf4.js","component---src-pages-404-js-a99c0d5feb017d0a2bf4.js.map"],"children":{},"childAssets":{}},"component---src-pages-about-js":{"chunks":[0,1,5],"assets":["styles.d19f409ceaaf3db55427.css","styles-efe02eb7393a36b75825.js","styles-efe02eb7393a36b75825.js.map","1-834dfe3fd661fe7c9a88.js","1-834dfe3fd661fe7c9a88.js.map","component---src-pages-about-js-8929f257445bb96fafe2.js","component---src-pages-about-js-8929f257445bb96fafe2.js.map"],"children":{},"childAssets":{}},"component---src-pages-index-js":{"chunks":[0,1,2,11,6],"assets":["styles.d19f409ceaaf3db55427.css","styles-efe02eb7393a36b75825.js","styles-efe02eb7393a36b75825.js.map","1-834dfe3fd661fe7c9a88.js","1-834dfe3fd661fe7c9a88.js.map","2-e6c9c74e3cf811e0f2ab.js","2-e6c9c74e3cf811e0f2ab.js.map","11-f8a0afecbf24cd71c2f4.js","11-f8a0afecbf24cd71c2f4.js.map","component---src-pages-index-js-5f473a85cbb6bfedb8ff.js","component---src-pages-index-js-5f473a85cbb6bfedb8ff.js.map"],"children":{},"childAssets":{}},"pages-manifest":{"chunks":[8],"assets":["pages-manifest-bf978cfd8bf0be819abd.js","pages-manifest-bf978cfd8bf0be819abd.js.map"],"children":{},"childAssets":{}}},"assetsByChunkName":{"app":["webpack-runtime-a1cdc5a2a5df1cf7ad58.js","app-832c7fb7645773a12e84.js"],"component---src-templates-establishment-page-js":["styles.d19f409ceaaf3db55427.css","styles-efe02eb7393a36b75825.js","1-834dfe3fd661fe7c9a88.js","2-e6c9c74e3cf811e0f2ab.js","10-1bfaa1cd3a83ccf05927.js","component---src-templates-establishment-page-js-658ebfa8996f0b5efdd1.js"],"component---src-pages-404-js":["styles.d19f409ceaaf3db55427.css","styles-efe02eb7393a36b75825.js","1-834dfe3fd661fe7c9a88.js","component---src-pages-404-js-a99c0d5feb017d0a2bf4.js"],"component---src-pages-about-js":["styles.d19f409ceaaf3db55427.css","styles-efe02eb7393a36b75825.js","1-834dfe3fd661fe7c9a88.js","component---src-pages-about-js-8929f257445bb96fafe2.js"],"component---src-pages-index-js":["styles.d19f409ceaaf3db55427.css","styles-efe02eb7393a36b75825.js","1-834dfe3fd661fe7c9a88.js","2-e6c9c74e3cf811e0f2ab.js","11-f8a0afecbf24cd71c2f4.js","component---src-pages-index-js-5f473a85cbb6bfedb8ff.js"],"pages-manifest":["pages-manifest-bf978cfd8bf0be819abd.js"]}}