{"data":{"postgres":{"establishment":[{"establishmentid":"2811","name":"Captain Jay's Fish & Chicken","address":"9623 Gratiot Ave","owner":"Amana Foods","licenseNumber":"054635","licenseType":"Fixed Establishment","establishmentType":"Food Service Establishment","establishmentStatus":"Permanently Closed","riskCategory":null,"reviewFrequencyDays":"180.0","inspectionsByEstablishmentidList":[{"inspectionid":"36267","inspectionDate":"2016-08-02T00:00:00","inspectionType":"Routine Inspection","inCompliance":"Yes","violationsByInspectionidList":[{"violationCode":"4-602.13","violationDescription":"NonFOOD-CONTACT SURFACES of EQUIPMENT shall be cleaned at a frequency necessary to preclude accumulation of soil residues.\r\n","violationType":"Core","itemDescription":"Nonfood contact surface(s)","subItem":"","problemDescription":"With accumulation of debris","subProblem":"","location":"KITCHEN (FRONT AREA)","subLocation":"","corrected":"Not required","daysToCorrect":"30.0","correctedDate":null,"correctionDescription":"Keep clean."}]}]}]}},"pageContext":{"eid":"2811"}}