{"data":{"site":{"pathPrefix":"/restaurant-inspections"},"postgres":{"establishment":[{"establishmentid":"51622672","name":"Cork & Gabel","address":"2415 Michigan Ave","zipcode":"48216","owner":"Joseph Mifsuld","licenseNumber":"ps","licenseType":"Fixed Establishment","establishmentType":"Food Service Establishment","establishmentStatus":"Open","riskCategory":"High","reviewFrequencyDays":"180.0","coords":"-83.07947,42.33112","geojson":{"id":"51622672","type":"Feature","geometry":{"type":"Point","coordinates":[-83.0794688729999,42.331118019]},"properties":{"name":"Cork & Gabel","owner":"Joseph Mifsuld","address":"2415 Michigan Ave","zipcode":"48216","license_type":"Fixed Establishment","risk_category":"High","license_number":"ps","establishmentid":"51622672","establishment_type":"Food Service Establishment","establishment_status":"Open","review_frequency_days":"180.0","most_recent_license_date":null}},"nearbyList":[{"establishmentid":"5113","name":"Takoi","address":"2520 Michigan Ave","zipcode":"48216"},{"establishmentid":"3745","name":"Mercury Burger Bar","address":"2163 Michigan Ave","zipcode":"48216"},{"establishmentid":"2950","name":"Slows BBQ","address":"2138 Michigan Ave","zipcode":"48216"},{"establishmentid":"4300","name":"Sugar House","address":"2130 Michigan Ave","zipcode":"48216"},{"establishmentid":"284","name":"L J'S Sweetheart bar","address":"2114 Michigan Ave","zipcode":"48216"},{"establishmentid":"5394","name":"Ima","address":"2015 Michigan Ave","zipcode":"48216"},{"establishmentid":"525","name":"Mexican Village Of Detroit","address":"2600 Bagley Street","zipcode":"48216"},{"establishmentid":"51622820","name":"Lucky Detroit Coffee & Espresso","address":"2000 Michigan","zipcode":"48216"},{"establishmentid":"5013","name":"Fist of Curry","address":"2547 Bagley Ave","zipcode":"48216"},{"establishmentid":"805","name":"Nancy Whiskey ","address":"2644 Harrison","zipcode":"48216"},{"establishmentid":"408","name":"Maltese Am Benevolent Society","address":"1832 Michigan Avenue","zipcode":"48216"},{"establishmentid":"407","name":"Casey's Pub d/b/a The Red Corridor","address":"1830 Michigan Ave","zipcode":"48216"},{"establishmentid":"1932","name":"Hernandez Center Head Start","address":"2051 Rosa Parks Blvd, Ste. 1K","zipcode":"48216"},{"establishmentid":"2653","name":"Burton International","address":"2001 Martin Luther King Blvd","zipcode":"48208"},{"establishmentid":"2656","name":"Valley Foods","address":"1980 Bagley","zipcode":"48216"},{"establishmentid":"1386","name":"Los Galanes","address":"3354 Bagley Ave","zipcode":"48216"},{"establishmentid":"642","name":"Xochimilco Restaurant ","address":"3401-09  Bagley","zipcode":"48216"},{"establishmentid":"1640","name":"University of Detroit Dental School","address":"2700 Martin L King Jr. Blvd","zipcode":"48208"},{"establishmentid":"51622463","name":"Corktown Tavern Inc.","address":"1716 Michigan Ave","zipcode":"48216"},{"establishmentid":"1454","name":"Mexican Town Restaurant","address":"3457 Bagley Street","zipcode":"48216"}],"inspectionsByEstablishmentidList":[{"inspectionid":"44421","inspectionDate":"2018-12-11T00:00:00","inspectionType":"Plan Review/Final/Ap","inCompliance":"Yes","violationsByInspectionidList":[]},{"inspectionid":"44394","inspectionDate":"2018-12-07T00:00:00","inspectionType":"Plan Review/Pre-Open","inCompliance":"Yes","violationsByInspectionidList":[]}]}]}},"pageContext":{"eid":"51622672"}}