{"data":{"postgres":{"establishment":[{"establishmentid":"2362","name":"Shirley Nelson's E & S Carryout","address":"13400 W McNichols Rd","zipcode":"48235","owner":"Delora Carter","licenseNumber":"043499","licenseType":"Fixed Establishment","mostRecentLicenseDate":"4/27/2018","establishmentType":"Food Service Establishment","establishmentStatus":"Open","riskCategory":"High","reviewFrequencyDays":"180.0","geom":"0101000020E6100000D0E4A4285ECB54C0804959425B354540","inspectionsByEstablishmentidList":[{"inspectionid":"44310","establishmentid":"2362","name":"Shirley Nelson's E & S Carryout","inspectionDate":"2018-11-28T00:00:00","inspectionType":"Routine Inspection","inspectorid":"127","pcount":"0","pfcount":"1","ccount":"0","criticalcount":"1","noncritical":"0","correctedcritical":"1","inCompliance":"Yes","violationsByInspectionidList":[{"inspectionid":"44310","inspectionDate":"11/28/2018","inspectionType":"Routine Inspection","establishmentid":"2362","name":"Shirley Nelson's E & S Carryout","violationCode":"7-102.11","violationDescription":"Working containers used for storing POISONOUS OR TOXIC MATERIALS such as cleaners and SANITIZERS taken from bulk supplies shall be clearly and individually identified with the common name of the material. (Pf)\r\n","violationType":"Foundation","criticalViolationType":"Yes","itemDescription":"Working containers-toxics","subItem":"cleaner","problemDescription":"Not labeled as to content","subProblem":"","location":"KITCHEN","subLocation":"","corrected":"Yes","daysToCorrect":"10.0","correctedDate":"2018-11-28T00:00:00","correctionDescription":"Label containers with common name."}]},{"inspectionid":"40256","establishmentid":"2362","name":"Shirley Nelson's E & S Carryout","inspectionDate":"2017-10-05T00:00:00","inspectionType":"Routine Inspection","inspectorid":"130","pcount":"0","pfcount":"0","ccount":"0","criticalcount":"0","noncritical":"0","correctedcritical":"0","inCompliance":"Yes","violationsByInspectionidList":[]},{"inspectionid":"38394","establishmentid":"2362","name":"Shirley Nelson's E & S Carryout","inspectionDate":"2017-03-29T00:00:00","inspectionType":"Routine Inspection","inspectorid":"130","pcount":"0","pfcount":"0","ccount":"0","criticalcount":"0","noncritical":"0","correctedcritical":"0","inCompliance":"Yes","violationsByInspectionidList":[]},{"inspectionid":"36658","establishmentid":"2362","name":"Shirley Nelson's E & S Carryout","inspectionDate":"2016-10-04T00:00:00","inspectionType":"Routine Inspection","inspectorid":"129","pcount":"0","pfcount":"0","ccount":"0","criticalcount":"0","noncritical":"0","correctedcritical":"0","inCompliance":"Yes","violationsByInspectionidList":[]}]}]}},"pageContext":{"eid":"2362"}}