{"data":{"postgres":{"establishment":[{"establishmentid":"4929","name":"Urban Elixirs Juice Bar","address":"19335 W McNichols Rd","zipcode":"48219","owner":"Heidi Norfleet","licenseNumber":"079477","licenseType":"Fixed Establishment","establishmentType":"Food Service Establishment","establishmentStatus":"Plan Review","riskCategory":"Medium","reviewFrequencyDays":"365.0","coords":"-83.23283,42.41503","geojson":{"id":"4929","type":"Feature","geometry":{"type":"Point","coordinates":[-83.232826997,42.415033878]},"properties":{"name":"Urban Elixirs Juice Bar","owner":"Heidi Norfleet","address":"19335 W McNichols Rd","zipcode":"48219","license_type":"Fixed Establishment","risk_category":"Medium","license_number":"079477","establishmentid":"4929","establishment_type":"Food Service Establishment","establishment_status":"Plan Review","review_frequency_days":"365.0","most_recent_license_date":"5/7/2018"}},"nearbyList":[{"establishmentid":"1093","name":"Church's Fried Chicken #456","address":"19741 W McNichols Rd","zipcode":"48219"},{"establishmentid":"4455","name":"Just a Bit Eclectic","address":"19015 W McNichols Rd","zipcode":"48219"},{"establishmentid":"2603","name":"Emerson Annex","address":"19500 Curtis Ave","zipcode":"48219"},{"establishmentid":"5412","name":"Detroit Vegan Soul","address":"19614 Grand River Ave","zipcode":"48223"},{"establishmentid":"2344","name":"Auntie Betty's Cafe","address":"19601 Grand River Ave","zipcode":"48223"},{"establishmentid":"907","name":"Emerson K-8 School","address":"18240 Huntington Ave","zipcode":"48219"},{"establishmentid":"1373","name":"Burger King ","address":"20200 Grand River Ave","zipcode":"48219"},{"establishmentid":"1958","name":"Hollywood Coney Island","address":"20240 Grand River Ave","zipcode":"48219"},{"establishmentid":"904","name":"Cooke Elementary","address":"18800 Puritan ","zipcode":"48219"},{"establishmentid":"1514","name":"Elias Donuts","address":"19231 Grand River Ave","zipcode":"48223"}],"inspectionsByEstablishmentidList":[{"inspectionid":"42635","inspectionDate":"2018-06-21T00:00:00","inspectionType":"Routine Inspection","inCompliance":"Yes","violationsByInspectionidList":[]},{"inspectionid":"39024","inspectionDate":"2017-06-13T00:00:00","inspectionType":"Routine Inspection","inCompliance":"Yes","violationsByInspectionidList":[]}]}]}},"pageContext":{"eid":"4929"}}