{"data":{"postgres":{"establishment":[{"establishmentid":"672","name":"Shelly's Smoking Sausage","address":"2727-31 Russell","owner":"Shelly L. Shepherd","licenseNumber":"034611","licenseType":"Mobile Food Establishment","establishmentType":"LHD - Mobile Food Establishmen","establishmentStatus":"Open","riskCategory":null,"reviewFrequencyDays":"395.0","coords":"-83.25211,42.46049","geojson":{"id":"672","type":"Feature","geometry":{"type":"Point","coordinates":[-83.252113293,42.4604867290001]},"properties":{"name":"Shelly's Smoking Sausage","owner":"Shelly L. Shepherd","address":"2727-31 Russell","zipcode":"48207","license_type":"Mobile Food Establishment","risk_category":null,"license_number":"034611","establishmentid":"672","establishment_type":"LHD - Mobile Food Establishmen","establishment_status":"Open","review_frequency_days":"395.0","most_recent_license_date":"5/18/2018"}},"nearbyList":[{"establishmentid":"415","name":"Popeye's Lousiana Kitchen","address":"20919 W Eight Mile Rd"},{"establishmentid":"51622605","name":"Asian Corn Beef","address":"21639 W Eight Mile Rd"},{"establishmentid":"688","name":"Trumpp's","address":"21413 W Eight Mile Rd"},{"establishmentid":"2775","name":"Penthouse","address":"20771 W Eight Mile Rd"},{"establishmentid":"518","name":"Friends Cocktail Lounge","address":"21633 W Eight Mile Rd"}],"inspectionsByEstablishmentidList":[{"inspectionid":"42332","inspectionDate":"2018-05-25T00:00:00","inspectionType":"Mobile Inspection","inCompliance":"Yes","violationsByInspectionidList":[]},{"inspectionid":"38699","inspectionDate":"2017-05-12T00:00:00","inspectionType":"Mobile Inspection","inCompliance":"Yes","violationsByInspectionidList":[]}]}]}},"pageContext":{"eid":"672"}}