{"data":{"postgres":{"establishment":[{"establishmentid":"4938","name":"UFO Factory","address":"2110 Trumbull St","zipcode":"48207","owner":null,"licenseNumber":"081268","licenseType":"Fixed Establishment","mostRecentLicenseDate":"4/19/2018","establishmentType":"Food Service Establishment","establishmentStatus":"Plan Review","riskCategory":"Medium","reviewFrequencyDays":"365.0","geom":"0101000020E6100000C41B316449C454C0C0FC2581842A4540","inspectionsByEstablishmentidList":[{"inspectionid":"44231","establishmentid":"4938","name":"UFO Factory","inspectionDate":"2018-10-15T00:00:00","inspectionType":"Routine Inspection","inspectorid":"124","pcount":"0","pfcount":"1","ccount":"0","criticalcount":"1","noncritical":"0","correctedcritical":"0","inCompliance":"No","violationsByInspectionidList":[{"inspectionid":"44231","inspectionDate":"10/15/2018","inspectionType":"Routine Inspection","establishmentid":"4938","name":"UFO Factory","violationCode":"4-302.14","violationDescription":"A test kit or other device that accurately measures the concentration in mg/L of SANITIZING solutions shall be provided. (Pf)\r\n","violationType":"Foundation","criticalViolationType":"Yes","itemDescription":"Sanitizer test kit","subItem":"","problemDescription":"Not provided","subProblem":"","location":"FACILITY","subLocation":"","corrected":"No","daysToCorrect":"10.0","correctedDate":null,"correctionDescription":"Provide."}]},{"inspectionid":"39168","establishmentid":"4938","name":"UFO Factory","inspectionDate":"2017-07-07T00:00:00","inspectionType":"Routine Inspection","inspectorid":"87","pcount":"0","pfcount":"0","ccount":"1","criticalcount":"0","noncritical":"1","correctedcritical":"0","inCompliance":"Yes","violationsByInspectionidList":[{"inspectionid":"39168","inspectionDate":"7/7/2017","inspectionType":"Routine Inspection","establishmentid":"4938","name":"UFO Factory","violationCode":"3-305.11","violationDescription":"FOOD shall be protected from contamination by storing the FOOD:\r\n(1)     In a clean, dry location;\r\n(2)     Where it is not exposed to splash, dust, or other contamination; and\r\n(3)     At least 15 cm (6 inches) above the floor, unless otherwise approved.\r\n","violationType":"Core","criticalViolationType":"No","itemDescription":"Food item(s) in storage","subItem":"","problemDescription":"Stored on floor or less than 6 inches above floor","subProblem":"","location":"BAR","subLocation":"Under the Bar","corrected":"Yes","daysToCorrect":"30.0","correctedDate":"2017-07-07T00:00:00","correctionDescription":"Store at least 6 inches above the floor."}]}]}]}},"pageContext":{"eid":"4938"}}