{"data":{"postgres":{"establishment":[{"establishmentid":"5284","name":"Conventional Missionary Baptist Church","address":"2255 Seminole","zipcode":"48214","owner":"Riderick Richardson","licenseNumber":"TEMP","licenseType":"Fixed Establishment","mostRecentLicenseDate":"4/28/2017","establishmentType":null,"establishmentStatus":null,"riskCategory":null,"reviewFrequencyDays":"90.0","geom":"0101000020E61000006CB09A5BDFBF54C09850D47B252E4540","inspectionsByEstablishmentidList":[]}]}},"pageContext":{"eid":"5284"}}