{"data":{"site":{"pathPrefix":"/restaurant-inspections"},"postgres":{"establishment":[{"establishmentid":"51623044","name":"Michigan & Trumbull/Fort Street Galley","address":"160 W Fort St","zipcode":"48226","owner":null,"licenseNumber":"062619JB","licenseType":"Fixed Establishment","establishmentType":"Food Service Establishment","establishmentStatus":"Permanently Closed","riskCategory":null,"reviewFrequencyDays":"90.0","coords":"-83.04859,42.33058","geojson":{"id":"51623044","type":"Feature","geometry":{"type":"Point","coordinates":[-83.048586349,42.330578971]},"properties":{"name":"Michigan & Trumbull/Fort Street Galley","owner":null,"address":"160 W Fort St","zipcode":"48226","license_type":"Fixed Establishment","risk_category":null,"license_number":"062619JB","establishmentid":"51623044","establishment_type":"Food Service Establishment","establishment_status":"Permanently Closed","review_frequency_days":"90.0","most_recent_license_date":null}},"nearbyList":[{"establishmentid":"51622866","name":"Isla/Fort Street Galley","address":"160 W Fort St","zipcode":"48226"},{"establishmentid":"5320","name":"Maru Detroit","address":"160 W Fort St","zipcode":"48226"},{"establishmentid":"51622868","name":"Pursue/Fort Street Galley","address":"160 W Fort St","zipcode":"48226"},{"establishmentid":"51622819","name":"Fort Street Galley- Bar & Table","address":"160 W Fort St","zipcode":"48226"},{"establishmentid":"51622867","name":"Allenby/Fort Street Galley","address":"160 W Fort St","zipcode":"48226"},{"establishmentid":"51622865","name":"Lucky's Noble BBQ/Fort Street Galley","address":"160 W Fort St","zipcode":"48226"},{"establishmentid":"51623307","name":"Kwench Juice ","address":"719 Griswold Ste 10","zipcode":"48226"},{"establishmentid":"51622853","name":"Kwench Juice Cafe'","address":"719 Griswold","zipcode":"48226"},{"establishmentid":"4866","name":"Dime Store","address":"719 Griswold St Ste 180","zipcode":"48226"},{"establishmentid":"5039","name":"Mikes Kabob Grille","address":"719 Griswold Ste 140","zipcode":"48226"}],"inspectionsByEstablishmentidList":[{"inspectionid":"49226","inspectionDate":"2019-09-23T00:00:00","inspectionType":"Routine Inspection","inCompliance":"Yes","violationsByInspectionidList":[{"violationCode":"3-501.18","violationDescription":"A FOOD specified in ¶ 3-501.17(A) or (B) shall be discarded if it:  \r\n    (1) Exceeds the temperature and time combination specified in ¶ 3-501.17(A),              except time that the product is frozen; (P)\r\n    (2) Is in a container or PACKAGE that does not bear a date or day; (P) or\r\n    (3) Is appropriately marked with a date or day that exceeds a temperature and              time combination as specified in ¶ 3-501.17(A). (P)  \r\n\r\n","violationType":"Priority","itemDescription":"Ready to eat, potentially hazardous food(s)","subItem":"","problemDescription":"Beyond consume by date","subProblem":"","location":"COOLER","subLocation":"Above the ACCESS","corrected":"Yes","daysToCorrect":"10","correctedDate":"2019-09-25T00:00:00","correctionDescription":null}]},{"inspectionid":"48267","inspectionDate":"2019-07-05T00:00:00","inspectionType":"Routine Inspection","inCompliance":"Yes","violationsByInspectionidList":[{"violationCode":"4-302.12","violationDescription":"(A) FOOD TEMPERATURE MEASURING DEVICES shall be provided and readily accessible for use in ensuring attainment and maintenance of FOOD temperatures as specified under Chapter 3. (Pf)   \r\n(B) A TEMPERATURE MEASURING DEVICE with a suitable small-diameter probe that is designed to measure the temperature of thin masses shall be provided and readily accessible to accurately measure the temperature in thin FOODS such as MEAT patties and FISH filets. (Pf)\r\n","violationType":"Foundation","itemDescription":"Food thermometer(s)","subItem":"probe","problemDescription":"Not provided","subProblem":"","location":"THERMOMETER","subLocation":"","corrected":"Yes","daysToCorrect":"10","correctedDate":"2019-08-05T00:00:00","correctionDescription":null}]}]}],"maxInspectionDate":[{"inspectionDate":"2020-10-30T00:00:00"}]}},"pageContext":{"eid":"51623044"}}