{"data":{"postgres":{"establishment":[{"establishmentid":"1131","name":"Clara Rutherford/Winans Academy","address":"16411 Curtis Ave","owner":"Detroit Board of Education","licenseNumber":"035209","licenseType":"Fixed Establishment","establishmentType":"Public School","establishmentStatus":"Open","riskCategory":"Medium","reviewFrequencyDays":"210.0","coords":"-83.20975,42.42246","geojson":{"id":"1131","type":"Feature","geometry":{"type":"Point","coordinates":[-83.209749307,42.4224643690001]},"properties":{"name":"Clara Rutherford/Winans Academy","owner":"Detroit Board of Education","address":"16411 Curtis Ave","zipcode":"48235","license_type":"Fixed Establishment","risk_category":"Medium","license_number":"035209","establishmentid":"1131","establishment_type":"Public School","establishment_status":"Open","review_frequency_days":"210.0","most_recent_license_date":"5/15/2017"}},"nearbyList":[{"establishmentid":"51622633","name":"Fellowship Chapel","address":"7707 W Outer Drive"},{"establishmentid":"4435","name":"Spud Headz","address":"16400 W McNichols Rd"},{"establishmentid":"2464","name":"Subway #24532","address":"7950 W Outer Dr"},{"establishmentid":"4974","name":"Motor City Sweet Shop","address":"16311 W Seven Mile Rd"},{"establishmentid":"5077","name":"Pasta Bowl","address":"17301 W McNichols Rd"}],"inspectionsByEstablishmentidList":[{"inspectionid":"43823","inspectionDate":"2018-10-18T00:00:00","inspectionType":"Routine Inspection","inCompliance":"Yes","violationsByInspectionidList":[]},{"inspectionid":"42028","inspectionDate":"2018-04-17T00:00:00","inspectionType":"Routine Inspection","inCompliance":"Yes","violationsByInspectionidList":[]},{"inspectionid":"40244","inspectionDate":"2017-09-27T00:00:00","inspectionType":"Routine Inspection","inCompliance":"Yes","violationsByInspectionidList":[{"violationCode":"7-102.11","violationDescription":"Working containers used for storing POISONOUS OR TOXIC MATERIALS such as cleaners and SANITIZERS taken from bulk supplies shall be clearly and individually identified with the common name of the material. (Pf)\r\n","violationType":"Foundation","itemDescription":"Working containers-toxics","subItem":"degreaser","problemDescription":"Not labeled as to content","subProblem":"","location":"KITCHEN","subLocation":"","corrected":"Yes","daysToCorrect":"10.0","correctedDate":"2017-09-27T00:00:00","correctionDescription":"Label containers with common name."},{"violationCode":"4-501.11","violationDescription":"EQUIPMENT shall be maintained in a state of repair and condition that meets the requirements of the code.\r\n","violationType":"Core","itemDescription":"Equipment","subItem":"","problemDescription":"In poor repair","subProblem":"Broken","location":"KITCHEN","subLocation":"","corrected":"Not required","daysToCorrect":"30.0","correctedDate":null,"correctionDescription":"Repair/replace."}]},{"inspectionid":"38964","inspectionDate":"2017-06-02T00:00:00","inspectionType":"Routine Inspection","inCompliance":"Yes","violationsByInspectionidList":[]},{"inspectionid":"36739","inspectionDate":"2016-10-12T00:00:00","inspectionType":"Routine Inspection","inCompliance":"Yes","violationsByInspectionidList":[]}]}]}},"pageContext":{"eid":"1131"}}